dm_tree-0.1.9.dist-info/LICENSE
dm_tree-0.1.9.dist-info/WHEEL
dm_tree-0.1.9.dist-info/RECORD
dm_tree-0.1.9.dist-info/top_level.txt
dm_tree-0.1.9.dist-info/METADATA
tree/sequence.py
tree/_tree.cpython-310-aarch64-linux-gnu.so
tree/tree_test.py
tree/__init__.py
tree/tree_benchmark.py
