Metadata-Version: 2.2
Name: dm-tree
Version: 0.1.9
Summary: Tree is a library for working with nested data structures.
Home-page: https://github.com/deepmind/tree
Author: DeepMind
Author-email: tree-copybara@google.com
License: Apache 2.0
Keywords: tree nest flatten
Classifier: Development Status :: 4 - Beta
Classifier: Intended Audience :: Developers
Classifier: Intended Audience :: Science/Research
Classifier: License :: OSI Approved :: Apache Software License
Classifier: Programming Language :: Python :: 3.10
Classifier: Programming Language :: Python :: 3.11
Classifier: Programming Language :: Python :: 3.12
Classifier: Programming Language :: Python :: 3.13
Classifier: Topic :: Scientific/Engineering :: Mathematics
Classifier: Topic :: Software Development :: Libraries
Requires-Python: >=3.10
License-File: LICENSE
Requires-Dist: absl-py>=0.6.1
Requires-Dist: attrs>=18.2.0
Requires-Dist: numpy>=1.21
Requires-Dist: numpy>=1.21.2; python_version >= "3.10"
Requires-Dist: numpy>=1.23.3; python_version >= "3.11"
Requires-Dist: numpy>=1.26.0; python_version >= "3.12"
Requires-Dist: numpy>=2.1.0; python_version >= "3.13"
Requires-Dist: wrapt>=1.11.2
Dynamic: author
Dynamic: author-email
Dynamic: classifier
Dynamic: description
Dynamic: description-content-type
Dynamic: home-page
Dynamic: keywords
Dynamic: license
Dynamic: requires-dist
Dynamic: requires-python
Dynamic: summary
